xml2epub/__init__.py
xml2epub/chapter.py
xml2epub/clean.py
xml2epub/constants.py
xml2epub/cover.py
xml2epub/epub.py
xml2epub/epub_cover/LXGWWenKai-Regular.ttf
xml2epub/epub_templates/container.xml
xml2epub/epub_templates/mimetype
xml2epub/epub_templates/opf.xml
xml2epub/epub_templates/toc.html
xml2epub/epub_templates/toc_ncx.xml
xml2epub-2.6.10.dist-info/METADATA
xml2epub-2.6.10.dist-info/WHEEL
xml2epub-2.6.10.dist-info/top_level.txt
xml2epub-2.6.10.dist-info/RECORD
