Metadata-Version: 2.1
Name: xml2epub
Version: 2.6.10
Summary: Batch convert multiple web pages, html files or images into one e-book.
Home-page: https://github.com/dfface/xml2epub
Author: dfface
Author-email: dfface@sina.com
License: UNKNOWN
Keywords: convert html url image export epub pypub html2epub
Platform: UNKNOWN
Classifier: Programming Language :: Python :: 3.7
Classifier: Programming Language :: Python :: 3.8
Classifier: Programming Language :: Python :: 3.9
Classifier: Programming Language :: Python :: 3.10
Classifier: Programming Language :: Python :: 3.11
Classifier: Programming Language :: Python :: 3.12
Classifier: Programming Language :: Python :: 3.13
Classifier: Programming Language :: Python :: 3 :: Only
Classifier: License :: OSI Approved :: MIT License
Classifier: Operating System :: OS Independent
Requires-Dist: beautifulsoup4
Requires-Dist: jinja2
Requires-Dist: requests
Requires-Dist: lxml
Requires-Dist: pillow
Requires-Dist: standard-imghdr
